Workbook

Sheet Historial de Ventas
A1: 📊 HISTORIAL DE VENTAS
A2: Generado el: 31/5/2026 | Sistema: MiTienda POS
A4: Factura N° | B4: Fecha | C4: Hora | D4: Items | E4: Subtotal | F4: IVA | G4: Impoconsumо | H4: Total | I4: Método de Pago | J4: Estado DIAN | K4: Observaciones
A5: 101 | B5: 2026-06-01 | C5: 10:00:00 | D5: ITEM A | E5: 100 | F5: 19 | G5: 0 | H5: 119 | I5: EFECTIVO | J5: Enviado DIAN
A6: 102 | B6: 2026-06-01 | C6: 11:00:00 | D6: ITEM B | E6: 200 | F6: 38 | G6: 0 | H6: 238 | I6: TARJETA | J6: Pendiente
A7: TOTALES | D7: =COUNTA(D5:D6) & " líneas" | E7: =SUM(E5:E6) | F7: =SUM(F5:F6) | G7: =SUM(G5:G6) | H7: =SUM(H5:H6)

Sheet Resumen
A1: RESUMEN DE VENTAS
A2: Métrica | B2: Valor
A3: Total de facturas | B3: =COUNTA('Historial de Ventas'!A5:A12) -> 0 | C3: =COUNTA('Historial de Ventas'!A5:A6)
A4: Ventas totales (neto) | B4: =SUM('Historial de Ventas'!E5:E12) -> 0 | C4: =SUM('Historial de Ventas'!E5:E6)
A5: Total IVA recaudado | B5: =SUM('Historial de Ventas'!F5:F12) -> 0 | C5: =SUM('Historial de Ventas'!F5:F6)
A6: Total Impoconsumo | B6: =SUM('Historial de Ventas'!G5:G12) -> 0 | C6: =SUM('Historial de Ventas'!G5:G6)
A7: Total recaudado | B7: =SUM('Historial de Ventas'!H5:H12) -> 0 | C7: =SUM('Historial de Ventas'!H5:H6)
A8: Facturas Enviado DIAN | B8: =COUNTIF('Historial de Ventas'!J5:J12,"Enviado DIAN") -> 0 | C8: =COUNTIF('Historial de Ventas'!J5:J6,"Enviado DIAN")
A9: Facturas Pendientes | B9: =COUNTIF('Historial de Ventas'!J5:J12,"Pendiente") -> 0 | C9: =COUNTIF('Historial de Ventas'!J5:J6,"Pendiente")
A10: Ventas EFECTIVO | B10: =SUMIF('Historial de Ventas'!I5:I12,"EFECTIVO",'Historial de Ventas'!H5:H12) -> 0 | C10: =SUMIF('Historial de Ventas'!I5:I6,"EFECTIVO",'Historial de Ventas'!H5:H6)
A11: Ventas TRANSFERENCIA | B11: =SUMIF('Historial de Ventas'!I5:I12,"TRANSFERENCIA",'Historial de Ventas'!H5:H12) -> 0 | C11: =SUMIF('Historial de Ventas'!I5:I6,"TRANSFERENCIA",'Historial de Ventas'!H5:H6)
A12: Ventas TARJETA | B12: =SUMIF('Historial de Ventas'!I5:I12,"TARJETA",'Historial de Ventas'!H5:H12) -> 0 | C12: =SUMIF('Historial de Ventas'!I5:I6,"TARJETA",'Historial de Ventas'!H5:H6)
